[{
  "Module_name": "Контрольная работа",
  "module_subject": "Биология",
  "quest_quantity": "22"
}, {
  "QUESTION_NUM": "1",
  "VAR": "1",
  "IMAGE": "",
  "QUESTION": "Какой уровень организации живого служит основным объектом изучения цитологии?",
  "A": "\r\nклеточный",
  "B": "биосферный",
  "C": "популяционно-видовой",
  "D": "биогеоценотический",
  "CORRECT": "\r\nклеточный",
  "NUM_ANSW": "4"
}, {
  "QUESTION_NUM": "2",
  "VAR": "1",
  "IMAGE": "",
  "QUESTION": "Почему при недостатке воды происходит увядание растений?",
  "A": "уменьшается давление клеточного сока на стенку вакуоли клетки",
  "B": "растение испытывает недостаток минеральных солей",
  "C": "снижается концентрация гормонов, влияющих на рост",
  "D": "падает активность фотосинтеза",
  "CORRECT": "уменьшается давление клеточного сока на стенку вакуоли клетки",
  "NUM_ANSW": "4"
}, {
  "QUESTION_NUM": "3",
  "VAR": "1",
  "IMAGE": "",
  "QUESTION": "У каких организмов реакция на раздражение проявляется в форме рефлекса?",
  "A": "одноклеточные растения",
  "B": "вирусы",
  "C": "бактерии",
  "D": "многоклеточные животные",
  "CORRECT": "одноклеточные растения",
  "NUM_ANSW": "4"
}, {
  "QUESTION_NUM": "4",
  "VAR": "1",
  "IMAGE": "",
  "QUESTION": "Если у растения одна семядоля в семени, то у него, скорее всего,",
  "A": "мочковатая корневая система",
  "B": "перисто-сетчатое жилкование",
  "C": "пальчатое жилкование",
  "D": "стержневая корневая система",
  "CORRECT": "мочковатая корневая система",
  "NUM_ANSW": "4"
}, {
  "QUESTION_NUM": "5",
  "VAR": "1",
  "IMAGE": "",
  "QUESTION": "Плод паслёновых растений картофеля и томата называют",
  "A": "ягодой",
  "B": "клубнем",
  "C": "корневой шишкой",
  "D": "корнеплодом",
  "CORRECT": "ягодой",
  "NUM_ANSW": "4"
}, {
  "QUESTION_NUM": "6",
  "VAR": "1",
  "IMAGE": "",
  "QUESTION": "У животных какой систематической группы сердце двухкамерное? ",
  "A": "Рыбы",
  "B": "Земноводные",
  "C": "Плоские черви",
  "D": "Насекомые",
  "CORRECT": "Рыбы",
  "NUM_ANSW": "4"
}, {
  "QUESTION_NUM": "7",
  "VAR": "1",
  "IMAGE": "",
  "QUESTION": "Температура окружающей среды существенно влияет на температуру тела",
  "A": "креветки",
  "B": "воробья",
  "C": "дельфина",
  "D": "пингвина",
  "CORRECT": "креветки",
  "NUM_ANSW": "4"
}, {
  "QUESTION_NUM": "8",
  "VAR": "1",
  "IMAGE": "",
  "QUESTION": "Какой признак человека характеризует его как представителя класса Млекопитающие?",
  "A": "имеется грудобрюшная перегородка – диафрагма",
  "B": "развивается замкнутая кровеносная система и два круга кровообращения",
  "C": "формируется внутренний костный скелет",
  "D": "на ранних стадиях эмбрионального развития формируется кишечная трубка",
  "CORRECT": "имеется грудобрюшная перегородка – диафрагма",
  "NUM_ANSW": "4"
}, {
  "QUESTION_NUM": "9",
  "VAR": "1",
  "IMAGE": "",
  "QUESTION": "Какая железа является железой внутренней секреции?",
  "A": "гипофиз",
  "B": "потовая",
  "C": "печень",
  "D": "слёзная",
  "CORRECT": "гипофиз",
  "NUM_ANSW": "4"
}, {
  "QUESTION_NUM": "10",
  "VAR": "1",
  "IMAGE": "",
  "QUESTION": "Подвижно соединены",
  "A": "ребра и грудина",
  "B": "позвонки крестцового отдела позвоночника ",
  "C": "кости мозгового отдела черепа",
  "D": "кости голени и стопы",
  "CORRECT": "ребра и грудина",
  "NUM_ANSW": "4"
}, {
  "QUESTION_NUM": "11",
  "VAR": "1",
  "IMAGE": "",
  "QUESTION": "Эритроциты могут переносить кислород и углекислый газ, так как в их цитоплазме содержится",
  "A": "гемоглобин",
  "B": "фибриноген",
  "C": "антитела",
  "D": "инсулин",
  "CORRECT": "гемоглобин",
  "NUM_ANSW": "4"
}, {
  "QUESTION_NUM": "12",
  "VAR": "1",
  "IMAGE": "",
  "QUESTION": "Термин «коронарные» употребляется при описании кровеносных сосудов, расположенных в тканях",
  "A": "мозга",
  "B": "почек",
  "C": "скелетных мышц",
  "D": "сердца",
  "CORRECT": "мозга",
  "NUM_ANSW": "4"
}, {
  "QUESTION_NUM": "13",
  "VAR": "1",
  "IMAGE": "",
  "QUESTION": "Легкие человека увеличиваются в объеме в результате",
  "A": "создания в плевральной полости отрицательного давления",
  "B": "изменения объема ротовой полости",
  "C": "притока крови в капилляры альвеол",
  "D": "диффузии атмосферного воздуха",
  "CORRECT": "создания в плевральной полости отрицательного давления",
  "NUM_ANSW": "4"
}, {
  "QUESTION_NUM": "14",
  "VAR": "1",
  "IMAGE": "",
  "QUESTION": "Структурной единицей почки является",
  "A": "нефрон ",
  "B": "каналец",
  "C": "капсула",
  "D": "нейрон",
  "CORRECT": "нефрон ",
  "NUM_ANSW": "4"
}, {
  "QUESTION_NUM": "15",
  "VAR": "1",
  "IMAGE": "",
  "QUESTION": "В какой части уха расположены слуховые косточки?",
  "A": "в полости среднего уха",
  "B": "в полости улитки",
  "C": "в наружном слуховом проходе",
  "D": "в полукружных каналах",
  "CORRECT": "в полости среднего уха",
  "NUM_ANSW": "4"
}, {
  "QUESTION_NUM": "16",
  "VAR": "1",
  "IMAGE": "",
  "QUESTION": "К безусловным рефлексам относят",
  "A": "отдёргивание руки от горячего предмета",
  "B": "умение управлять машиной",
  "C": "чтение художественной литературы",
  "D": "использование словесных символов",
  "CORRECT": "отдёргивание руки от горячего предмета",
  "NUM_ANSW": "4"
}, {
  "QUESTION_NUM": "17",
  "VAR": "1",
  "IMAGE": "",
  "QUESTION": "Раствором какого вещества необходимо обработать кожу при ожоге кислотой после промывания места ожога водой?",
  "A": "соды",
  "B": "уксуса",
  "C": "пищевой соли",
  "D": "йода",
  "CORRECT": "соды",
  "NUM_ANSW": "4"
}, {
  "QUESTION_NUM": "18",
  "VAR": "1",
  "IMAGE": "",
  "QUESTION": "Приспособленность кактусов к засушливым условиям пустыни состоит  в том, что у них",
  "A": "устьица расположены на нижней части листа",
  "B": "корни уходят глубоко в почву, поглощают много воды",
  "C": "прекращаются все процессы жизнедеятельности",
  "D": "в стеблях имеются водоносные ткани, в которых они запасают воду",
  "CORRECT": "устьица расположены на нижней части листа",
  "NUM_ANSW": "4"
}, {
  "QUESTION_NUM": "19",
  "VAR": "1",
  "IMAGE": "",
  "QUESTION": "Какая из перечисленных групп растений в ходе эволюции первой перестала зависеть при оплодотворении от наличия воды?",
  "A": "Голосеменные",
  "B": "Папоротникообразные",
  "C": "Мхи",
  "D": "Покрытосеменнные",
  "CORRECT": "Голосеменные",
  "NUM_ANSW": "4"
}]
